tf_siren/__init__.py
tf_siren/encoder.py
tf_siren/hypernet.py
tf_siren/siren.py
tf_siren/siren_mlp.py
tf_siren/meta/__init__.py
tf_siren/meta/meta_siren.py
tf_siren/meta/meta_siren_mlp.py
tf_siren-0.0.5.dist-info/LICENSE
tf_siren-0.0.5.dist-info/METADATA
tf_siren-0.0.5.dist-info/WHEEL
tf_siren-0.0.5.dist-info/top_level.txt
tf_siren-0.0.5.dist-info/RECORD
