Metadata-Version: 2.1
Name: tf-siren
Version: 0.0.5
Summary: Tensorflow 2.0 implementation of Sinusodial Representation networks (SIREN).
Home-page: https://github.com/titu1994/tf_SIREN
Author: Somshubra Majumdar
Author-email: titu1994@gmail.com
License: MIT
Download-URL: https://github.com/titu1994/tf_SIREN
Platform: UNKNOWN
Classifier: Programming Language :: Python :: 3
Classifier: Programming Language :: Python :: 3.5
Classifier: Programming Language :: Python :: 3.6
Classifier: Programming Language :: Python :: 3.7
Classifier: License :: OSI Approved :: MIT License
Classifier: Operating System :: OS Independent
Classifier: Topic :: Software Development :: Libraries
Classifier: Topic :: Software Development :: Libraries :: Python Modules
Requires-Python: >=3.0.0
Requires-Dist: tensorflow (>=2.2.0)
Requires-Dist: numpy (>=1.16.2)
Requires-Dist: tqdm (>=4.44.1)
Provides-Extra: cpu
Requires-Dist: tensorflow (>=2.2.0) ; extra == 'cpu'
Provides-Extra: gpu
Requires-Dist: tensorflow (>=2.2.0) ; extra == 'gpu'
Provides-Extra: tests
Requires-Dist: pytest ; extra == 'tests'
Requires-Dist: scipy ; extra == 'tests'
